artella/__init__.py
artella/__version__.py
artella/_version.py
artella/api.py
artella/dcc.py
artella/loader.py
artella/logging.ini
artella/core/__init__.py
artella/core/callbacks.py
artella/core/client.py
artella/core/consts.py
artella/core/dccplugin.py
artella/core/downloader.py
artella/core/exceptions.py
artella/core/plugin.py
artella/core/plugins.py
artella/core/project.py
artella/core/qtutils.py
artella/core/resource.py
artella/core/splash.py
artella/core/utils.py
artella/core/dcc/__init__.py
artella/core/dcc/callback.py
artella/core/dcc/dialog.py
artella/core/dcc/parser.py
artella/core/dcc/progress.py
artella/core/dcc/ui.py
artella/core/dcc/window.py
artella/dccs/__init__.py
artella/externals/Qt.py
artella/externals/__init__.py
artella/plugins/__init__.py
artella/resources/icons/artella.png
artella/resources/icons/artella_white.png
artella/resources/icons/close.png
artella/resources/icons/error.png
artella/resources/icons/info.png
artella/resources/icons/success.png
artella/resources/icons/warning.png
artella/resources/images/artella_header.png
artella/resources/images/artella_splash.png
artella/resources/styles/artella.css
artella/widgets/__init__.py
artella/widgets/button.py
artella/widgets/color.py
artella/widgets/divider.py
artella/widgets/image.py
artella/widgets/label.py
artella/widgets/snackbar.py
artella/widgets/stack.py
artella/widgets/theme.py
tests/__init__.py
tests/test_client.py
artella_plugins_core-1.0.28.dist-info/METADATA
artella_plugins_core-1.0.28.dist-info/WHEEL
artella_plugins_core-1.0.28.dist-info/top_level.txt
artella_plugins_core-1.0.28.dist-info/RECORD
