Metadata-Version: 2.1
Name: artella-plugins-core
Version: 1.0.28
Summary: Core Artella plugin package to create DCC plugins for Artella.
Home-page: https://github.com/artella/artella-plugins-core
Author: Artella, Inc
Author-email: support@artella.com
License: UNKNOWN
Platform: UNKNOWN
Requires-Dist: Qt.py
Requires-Dist: PySide ; python_version < "2.7" and sys_platform == "darwin"
Requires-Dist: PySide ; python_version <= "3.4" and sys_platform == "win32"
Requires-Dist: PySide2 ; python_version > "3.4" and sys_platform == "win32"
Requires-Dist: PySide2 ; python_version >= "2.7" and sys_platform == "darwin"
Provides-Extra: dev
Requires-Dist: wheel ; extra == 'dev'
Provides-Extra: test
Requires-Dist: pytest ; extra == 'test'
